py_parse/__init__.py
py_parse/base.py
py_parse/exceptions.py
py_parse/helpers.py
py_parse/node.py
py_parse/nodes.py
py_parse/parser.py
py_parse-0.2.0.dist-info/LICENSE
py_parse-0.2.0.dist-info/METADATA
py_parse-0.2.0.dist-info/WHEEL
py_parse-0.2.0.dist-info/top_level.txt
py_parse-0.2.0.dist-info/RECORD
