Metadata-Version: 2.1
Name: py-parse
Version: 0.2.0
Summary: A simplest HTML parsing library.
Home-page: https://bitbucket.org/kotolex/html_parser
Author: Lex Draven
Author-email: lexman2@yandex.ru
License: UNKNOWN
Platform: UNKNOWN
Classifier: Programming Language :: Python :: 3
Classifier: License :: OSI Approved :: MIT License
Classifier: Operating System :: OS Independent
Requires-Python: >=3.7
